django_magic_cards-0.4.1.dist-info/DESCRIPTION.rst
django_magic_cards-0.4.1.dist-info/METADATA
django_magic_cards-0.4.1.dist-info/RECORD
django_magic_cards-0.4.1.dist-info/WHEEL
django_magic_cards-0.4.1.dist-info/metadata.json
django_magic_cards-0.4.1.dist-info/top_level.txt
magic_cards/__init__.py
magic_cards/admin.py
magic_cards/apps.py
magic_cards/models.py
magic_cards/management/__init__.py
magic_cards/management/commands/__init__.py
magic_cards/management/commands/import_magic_cards.py
magic_cards/migrations/0001_initial.py
magic_cards/migrations/0002_card_loyalty.py
magic_cards/migrations/__init__.py
magic_cards/utils/__init__.py
magic_cards/utils/import_cards.py
magic_cards/utils/initial_import.py
magic_cards/utils/random.py
