Metadata-Version: 2.0
Name: django-magic-cards
Version: 0.4.1
Summary: A Django app for the Oracle text of all Magic: the Gathering cards.
Home-page: https://github.com/pbaranay/django-magic-cards
Author: Paul Baranay
Author-email: pbaranay@gmail.com
License: MIT
Keywords: django-magic-cards
Platform: UNKNOWN
Classifier: Development Status :: 3 - Alpha
Classifier: Framework :: Django
Classifier: Framework :: Django :: 1.8
Classifier: Framework :: Django :: 1.9
Classifier: Framework :: Django :: 1.10
Classifier: Framework :: Django :: 1.11
Classifier: Intended Audience :: Developers
Classifier: License :: OSI Approved :: BSD License
Classifier: Programming Language :: Python :: 2
Classifier: Programming Language :: Python :: 2.7
Classifier: Programming Language :: Python :: 3
Classifier: Programming Language :: Python :: 3.3
Classifier: Programming Language :: Python :: 3.4
Classifier: Programming Language :: Python :: 3.5
Classifier: Topic :: Games/Entertainment
Requires-Dist: django-light-enums (>=0.1.6)
Requires-Dist: inflect (>=0.2.5)
Requires-Dist: requests (>=2.18.2)
